spacy_trankit/__init__.py
spacy_trankit/tokenizer.py
spacy_trankit/version.py
spacy_trankit-0.1.0.dist-info/LICENSE
spacy_trankit-0.1.0.dist-info/METADATA
spacy_trankit-0.1.0.dist-info/WHEEL
spacy_trankit-0.1.0.dist-info/top_level.txt
spacy_trankit-0.1.0.dist-info/RECORD
