Metadata-Version: 2.1
Name: spacy-trankit
Version: 0.1.0
Summary: spacy wrapper for Trankit, a Transformer-based multilingual neural dependency parser with tokenization and NER
Home-page: https://github.com/imvladikon/spacy-trankit
Author: Vladimir Gurevich
Classifier: Programming Language :: Python :: 3
Classifier: Topic :: Scientific/Engineering
Requires-Python: >=3.8
License-File: LICENSE
Requires-Dist: nltk
Requires-Dist: spacy
Requires-Dist: trankit
